AUTHORS
LICENSE
README.rst
setup.py
re_ver.egg-info/PKG-INFO
re_ver.egg-info/SOURCES.txt
re_ver.egg-info/dependency_links.txt
re_ver.egg-info/not-zip-safe
re_ver.egg-info/requires.txt
re_ver.egg-info/top_level.txt
rever/__init__.py
rever/__main__.py
rever/activity.xsh
rever/authors.xsh
rever/conda.xsh
rever/dag.py
rever/docker.xsh
rever/environ.xsh
rever/github.xsh
rever/logger.xsh
rever/main.xsh
rever/sat.xsh
rever/tools.xsh
rever/vcsutils.xsh
rever/activities/__init__.py
rever/activities/appimage.xsh
rever/activities/authors.xsh
rever/activities/bibtex.xsh
rever/activities/changelog.xsh
rever/activities/check.xsh
rever/activities/command.xsh
rever/activities/conda_forge.xsh
rever/activities/docker.xsh
rever/activities/forge.xsh
rever/activities/gcloud.xsh
rever/activities/ghpages.xsh
rever/activities/ghrelease.xsh
rever/activities/nose.xsh
rever/activities/push_tag.xsh
rever/activities/pypi.xsh
rever/activities/pytest.xsh
rever/activities/sphinx.xsh
rever/activities/tag.xsh
rever/activities/version_bump.xsh
scripts/rever