Metadata-Version: 2.1
Name: re-ver
Version: 0.5.1
Summary: Release Versions of Software
Home-page: https://github.com/scopatz/rever
Author: Anthony Scopatz
Author-email: scopatz@gmail.com
Maintainer: Anthony Scopatz
License: BSD
Platform: Cross Platform
Classifier: Programming Language :: Python :: 3
Requires-Python: >3.4
License-File: LICENSE
License-File: AUTHORS
